[
    {
        "title": "Test Title",
        "text": "Test text"
    },
    {
        "title": "note test",
        "text": "this is a test",
        "note_id": "85135d1b-b29e-4ba6-af65-1f505de5fb5e"
    },
    {
        "title": "this is another test",
        "text": "note",
        "note_id": "12014869-0220-4035-bdec-25ef4b05d2df"
    },
    {
        "title": "test",
        "text": "test",
        "note_id": "b1751fab-012e-42ac-9611-1449978d1906"
    },
    {
        "title": "test run",
        "text": "hopefully this works",
        "note_id": "85adc5b6-ae59-41e7-ac3e-d1811a3ce43f"
    },
    {
        "title": "www",
        "text": ".com",
        "note_id": "cdd61830-8924-43bf-8c99-c974f9942ced"
    }
]